pyminusone-0.4.1.dist-info/METADATA
pyminusone-0.4.1.dist-info/WHEEL
pyminusone/__init__.py
pyminusone/pyminusone.abi3.so
pyminusone-0.4.1.dist-info/RECORD
